docx_comments/__init__.py
docx_comments/anchors.py
docx_comments/manager.py
docx_comments/models.py
docx_comments/py.typed
docx_comments/system_author.py
docx_comments/xml_parts.py
docx_comments-0.3.0.dist-info/METADATA
docx_comments-0.3.0.dist-info/WHEEL
docx_comments-0.3.0.dist-info/licenses/LICENSE
docx_comments-0.3.0.dist-info/RECORD
