Metadata-Version: 2.4
Name: docx-comments
Version: 0.3.0
Summary: Complete Word document comment manipulation with threading and Word Online compatibility
Project-URL: Homepage, https://github.com/sunt05/docx-comments
Project-URL: Repository, https://github.com/sunt05/docx-comments
Project-URL: Issues, https://github.com/sunt05/docx-comments/issues
Author-email: Ting Sun <ting.sun@ucl.ac.uk>
License: MIT
License-File: LICENSE
Keywords: comments,docx,ooxml,python-docx,word
Classifier: Development Status :: 3 - Alpha
Classifier: Intended Audience :: Developers
Classifier: License :: OSI Approved :: MIT License
Classifier: Programming Language :: Python :: 3
Classifier: Programming Language :: Python :: 3.9
Classifier: Programming Language :: Python :: 3.10
Classifier: Programming Language :: Python :: 3.11
Classifier: Programming Language :: Python :: 3.12
Classifier: Programming Language :: Python :: 3.13
Classifier: Topic :: Office/Business :: Office Suites
Classifier: Topic :: Text Processing :: Markup :: XML
Requires-Python: >=3.9
Requires-Dist: lxml>=4.9.0
Requires-Dist: python-docx>=1.0.0
Provides-Extra: dev
Requires-Dist: mypy>=1.0; extra == 'dev'
Requires-Dist: pytest-cov>=4.0; extra == 'dev'
Requires-Dist: pytest>=7.0; extra == 'dev'
Requires-Dist: ruff>=0.1.0; extra == 'dev'
